__init__.py
globals.py
lepus.py
collectors/CRT.py
collectors/Censys.py
collectors/CertSpotter.py
collectors/DNSTrails.py
collectors/FOFA.py
collectors/GoogleTransparency.py
collectors/HackerTarget.py
collectors/PDChaos.py
collectors/PassiveTotal.py
collectors/ProjectCrobat.py
collectors/ProjectSonar.py
collectors/Riddler.py
collectors/Shodan.py
collectors/Spyse.py
collectors/ThreatCrowd.py
collectors/ThreatMiner.py
collectors/VirusTotal.py
collectors/WaybackMachine.py
collectors/ZoomEye.py
collectors/__init__.py
submodules/Markov.py
submodules/Permutations.py
submodules/PortScan.py
submodules/RIPE.py
submodules/ReverseLookups.py
submodules/TakeOver.py
submodules/__init__.py
utilities/DatabaseHelpers.py
utilities/MiscHelpers.py
utilities/ScanHelpers.py
utilities/__init__.py
lepus_neo-1.0.0.dist-info/LICENSE
lepus_neo-1.0.0.dist-info/METADATA
lepus_neo-1.0.0.dist-info/WHEEL
lepus_neo-1.0.0.dist-info/entry_points.txt
lepus_neo-1.0.0.dist-info/top_level.txt
lepus_neo-1.0.0.dist-info/RECORD
