Metadata-Version: 2.1
Name: lepus-neo
Version: 1.0.0
Summary: Lepus is a tool for enumerating subdomains, checking for subdomain takeovers and perform port scans - and boy, is it fast!
Author: gfek
Author-email: Lilly Aronleigh <ghostoverflow256@gmail.com>
Project-URL: Homepage, https://github.com/GhostDog98/lepus-neo
Project-URL: Issues, https://github.com/GhostDog98/lepus-neo
Classifier: Programming Language :: Python :: 3
Classifier: License :: OSI Approved :: BSD License
Classifier: Operating System :: OS Independent
Requires-Python: >=3.7
License-File: LICENSE
Requires-Dist: setuptools
Requires-Dist: beautifulsoup4 ==4.9.3
Requires-Dist: dnspython ==2.0.0
Requires-Dist: ipwhois ==1.2.0
Requires-Dist: requests ==2.32.2
Requires-Dist: shodan ==1.25.0
Requires-Dist: slackclient ==2.9.3
Requires-Dist: SQLAlchemy ==1.4.18
Requires-Dist: termcolor ==1.1.0
Requires-Dist: tqdm ==4.61.1
